ghau/__init__.py
ghau/errors.py
ghau/files.py
ghau/update.py
ghau-0.4.dist-info/LICENSE
ghau-0.4.dist-info/METADATA
ghau-0.4.dist-info/WHEEL
ghau-0.4.dist-info/top_level.txt
ghau-0.4.dist-info/RECORD
