Metadata-Version: 2.1
Name: ghau
Version: 0.4
Summary: Github Auto Update package using Github releases.
Home-page: https://www.github.com/InValidFire/ghau
Author: Elizabeth Housden
Author-email: wolvie2013@gmail.com
License: MIT License
Platform: UNKNOWN
Requires-Dist: invalidfire-utils (>=2020.10.9.1)
Requires-Dist: PyGithub (>=1.51)
Requires-Dist: requests (>=2.23.0)
